yata/__init__.py
yata/augmix.py
yata/cmd_tools.py
yata/convnet.py
yata/feature.py
yata/mixup.py
yata/multi_scale_mel.py
yata/pcm_tool.py
yata/spectaug.py
yata/transform.py
yata/util.py
yata/version.py
libyata-0.7.8.dist-info/LICENSE
libyata-0.7.8.dist-info/METADATA
libyata-0.7.8.dist-info/WHEEL
libyata-0.7.8.dist-info/entry_points.txt
libyata-0.7.8.dist-info/top_level.txt
libyata-0.7.8.dist-info/RECORD
