Metadata-Version: 2.1
Name: libyata
Version: 0.7.8
Summary: Yet Another Tools for Audio deep learning
Home-page: http://github.com/HudsonHuang/yata
Author: HudsonHuang
Author-email: 790209714@qq.com
License: MIT
Keywords: deep learning,audio processing,machine learning
Classifier: License :: OSI Approved :: ISC License (ISCL)
Classifier: Programming Language :: Python
Classifier: Development Status :: 3 - Alpha
Classifier: Intended Audience :: Developers
Classifier: Topic :: Multimedia :: Sound/Audio :: Analysis
Classifier: Programming Language :: Python :: 2
Classifier: Programming Language :: Python :: 2.7
Classifier: Programming Language :: Python :: 3
Classifier: Programming Language :: Python :: 3.4
Classifier: Programming Language :: Python :: 3.5
Classifier: Programming Language :: Python :: 3.6
Classifier: Programming Language :: Python :: 3.7
License-File: LICENSE
Requires-Dist: webrtcvad
Requires-Dist: fire
Requires-Dist: numpy
